dls_utilpack/__init__.py
dls_utilpack/__main__.py
dls_utilpack/_version.py
dls_utilpack/bash_composer.py
dls_utilpack/callsign.py
dls_utilpack/client_context_base.py
dls_utilpack/datatypes.py
dls_utilpack/describe.py
dls_utilpack/envvar.py
dls_utilpack/exceptions.py
dls_utilpack/explain.py
dls_utilpack/global_signals.py
dls_utilpack/hazzathread.py
dls_utilpack/ignore.py
dls_utilpack/import_class.py
dls_utilpack/isodatetime.py
dls_utilpack/modify_process_title.py
dls_utilpack/module.py
dls_utilpack/profiler.py
dls_utilpack/qualname.py
dls_utilpack/require.py
dls_utilpack/sanitize.py
dls_utilpack/search_file.py
dls_utilpack/server_context_base.py
dls_utilpack/signal.py
dls_utilpack/substitute.py
dls_utilpack/thing.py
dls_utilpack/things.py
dls_utilpack/version.py
dls_utilpack/visit.py
dls_utilpack/whatenv.py
dls_utilpack-1.6.1.dist-info/LICENSE
dls_utilpack-1.6.1.dist-info/METADATA
dls_utilpack-1.6.1.dist-info/WHEEL
dls_utilpack-1.6.1.dist-info/entry_points.txt
dls_utilpack-1.6.1.dist-info/top_level.txt
dls_utilpack-1.6.1.dist-info/RECORD
