Metadata-Version: 2.1
Name: dls-utilpack
Version: 1.6.1
Summary: Library of various useful Python classes and functions.
Author-email: David Erb <david.erb@diamond.ac.uk>
License: Apache License
Project-URL: GitLab, https://gitlab.diamond.ac.uk/scisoft/dls-utilpack
Classifier: Development Status :: 3 - Alpha
Classifier: License :: OSI Approved :: Apache Software License
Classifier: Programming Language :: Python :: 3.9
Classifier: Programming Language :: Python :: 3.10
Classifier: Programming Language :: Python :: 3.11
Requires-Python: >=3.9
License-File: LICENSE
Requires-Dist: dls-logformatter
Requires-Dist: prettytable
Requires-Dist: ruamel.yaml
Requires-Dist: setproctitle
Provides-Extra: dev
Requires-Dist: black (==22.12.0) ; extra == 'dev'
Requires-Dist: mypy ; extra == 'dev'
Requires-Dist: flake8-isort ; extra == 'dev'
Requires-Dist: Flake8-pyproject ; extra == 'dev'
Requires-Dist: pipdeptree ; extra == 'dev'
Requires-Dist: pre-commit ; extra == 'dev'
Requires-Dist: pytest-cov ; extra == 'dev'
Requires-Dist: pydocstyle[toml] ; extra == 'dev'
Requires-Dist: tox-direct ; extra == 'dev'
Requires-Dist: types-mock ; extra == 'dev'
Requires-Dist: types-PyYAML ; extra == 'dev'
Provides-Extra: docs
Requires-Dist: pydata-sphinx-theme (>=0.12) ; extra == 'docs'
Requires-Dist: sphinx-argparse ; extra == 'docs'
Requires-Dist: sphinx-autobuild ; extra == 'docs'
Requires-Dist: sphinx-copybutton ; extra == 'docs'
Requires-Dist: sphinx-design ; extra == 'docs'
Requires-Dist: tox-direct ; extra == 'docs'
Requires-Dist: nbsphinx ; extra == 'docs'
Requires-Dist: pandoc ; extra == 'docs'
Requires-Dist: ipykernel ; extra == 'docs'
Requires-Dist: h5py ; extra == 'docs'
Requires-Dist: matplotlib ; extra == 'docs'
